[
    {
        "General": {
            "name": "Background",
            "tag": 4,
            "subtag": 0,
            "isActive": true
        },
        "Transform": {
            "scale": {
                "X": 1600.0,
                "Y": 900.0
            },
            "rotation": 0.0,
            "translation": {
                "X": 0.0,
                "Y": 0.0
            }
        },
        "Sprite": {
            "color": {
                "r": 255,
                "g": 255,
                "b": 255,
                "a": 255
            },
            "sprite": 2,
            "texture": "Textures\\Menu\\menu screen background.jpg",
            "layer": 0
        }
    },
    {
        "General": {
            "name": "How_To_Play",
            "tag": 8,
            "subtag": 0,
            "isActive": true
        },
        "Transform": {
            "scale": {
                "X": 1186.0,
                "Y": 692.0
            },
            "rotation": 0.0,
            "translation": {
                "X": 0.0,
                "Y": 0.0
            }
        },
        "Sprite": {
            "color": {
                "r": 255,
                "g": 255,
                "b": 255,
                "a": 255
            },
            "sprite": 2,
            "texture": "Textures\\Menu\\window-1.png",
            "layer": 1
        },
        "Text": {
            "fontFile": "BPtypewrite",
            "text": "HOW TO PLAY",
            "offset": {
                "X": -243.0,
                "Y": 200.0
            },
            "scale": 1.5,
            "color": {
                "r": 255,
                "g": 255,
                "b": 255,
                "a": 255
            }
        }
    },
    {
        "General": {
            "name": "Back",
            "tag": 5,
            "subtag": 1,
            "isActive": true
        },
        "Transform": {
            "scale": {
                "X": 650.0,
                "Y": 150.0
            },
            "rotation": 0.0,
            "translation": {
                "X": 0.0,
                "Y": -335.0
            }
        },
        "Sprite": {
            "color": {
                "r": 255,
                "g": 255,
                "b": 255,
                "a": 255
            },
            "sprite": 2,
            "texture": "Textures\\Menu\\button1-click.png",
            "layer": 2
        },
        "CircleCollider": {
            "centerOffset": {
                "X": 0.0,
                "Y": 0.0
            },
            "scaleOffset": 1.0,
            "isTrigger": false,
            "renderFlag": false
        },
        "Audio": {
            "path": "Button_Click_SFX",
            "volume": 1.0,
            "volumeMod": 1.0,
            "pitch": 1.0,
            "isPaused": false,
            "isMute": false,
            "isLoop": false,
            "isRandPitch": false,
            "isSpacial": false
        },
        "Text": {
            "fontFile": "BPtypewrite",
            "text": "Back",
            "offset": {
                "X": -59.0,
                "Y": -19.0
            },
            "scale": 1.0,
            "color": {
                "r": 255,
                "g": 255,
                "b": 255,
                "a": 255
            }
        },
        "Button": {
            "interactable": true
        }
    },
    {
        "General": {
            "name": "Instruction 1",
            "tag": 5,
            "subtag": 0,
            "isActive": true
        },
        "Transform": {
            "scale": {
                "X": 504.0,
                "Y": 150.0
            },
            "rotation": 0.0,
            "translation": {
                "X": 89.74580383300781,
                "Y": 135.47454833984375
            }
        },
        "Sprite": {
            "color": {
                "r": 0,
                "g": 255,
                "b": 0,
                "a": 0
            },
            "sprite": 1,
            "texture": "",
            "layer": 3
        },
        "Text": {
            "fontFile": "BPtypewrite",
            "text": "Move Player",
            "offset": {
                "X": -173.0,
                "Y": -78.0
            },
            "scale": 0.8999999761581421,
            "color": {
                "r": 255,
                "g": 255,
                "b": 255,
                "a": 255
            }
        }
    },
    {
        "General": {
            "name": "Instruction 2",
            "tag": 5,
            "subtag": 0,
            "isActive": true
        },
        "Transform": {
            "scale": {
                "X": 594.0,
                "Y": 150.0
            },
            "rotation": 0.0,
            "translation": {
                "X": 168.99154663085938,
                "Y": 14.614002227783203
            }
        },
        "Sprite": {
            "color": {
                "r": 0,
                "g": 255,
                "b": 0,
                "a": 0
            },
            "sprite": 1,
            "texture": "",
            "layer": 4
        },
        "Text": {
            "fontFile": "BPtypewrite",
            "text": "Advance Dialogue",
            "offset": {
                "X": -253.0,
                "Y": -18.0
            },
            "scale": 0.8999999761581421,
            "color": {
                "r": 255,
                "g": 255,
                "b": 255,
                "a": 255
            }
        }
    },
    {
        "General": {
            "name": "Cursor",
            "tag": 5,
            "subtag": 0,
            "isActive": true
        },
        "Transform": {
            "scale": {
                "X": 90.0,
                "Y": 90.0
            },
            "rotation": 0.0,
            "translation": {
                "X": -232.0,
                "Y": -132.0
            }
        },
        "Sprite": {
            "color": {
                "r": 0,
                "g": 255,
                "b": 0,
                "a": 0
            },
            "sprite": 0,
            "texture": "",
            "layer": 2
        },
        "Text": {
            "fontFile": "BPtypewrite",
            "text": "ESC",
            "offset": {
                "X": -42.0,
                "Y": -16.0
            },
            "scale": 1.0,
            "color": {
                "r": 255,
                "g": 255,
                "b": 255,
                "a": 255
            }
        }
    },
    {
        "General": {
            "name": "Instruction 1",
            "tag": 5,
            "subtag": 0,
            "isActive": true
        },
        "Transform": {
            "scale": {
                "X": 379.0,
                "Y": 150.0
            },
            "rotation": 0.0,
            "translation": {
                "X": 93.51278686523438,
                "Y": -69.32334899902344
            }
        },
        "Sprite": {
            "color": {
                "r": 0,
                "g": 255,
                "b": 0,
                "a": 0
            },
            "sprite": 1,
            "texture": "",
            "layer": 3
        },
        "Text": {
            "fontFile": "BPtypewrite",
            "text": "Pause Menu",
            "offset": {
                "X": -173.0,
                "Y": -78.0
            },
            "scale": 0.8999999761581421,
            "color": {
                "r": 255,
                "g": 255,
                "b": 255,
                "a": 255
            }
        }
    },
    {
        "General": {
            "name": "NEW Entity 1",
            "tag": 8,
            "subtag": 0,
            "isActive": true
        },
        "Transform": {
            "scale": {
                "X": 90.0,
                "Y": 90.0
            },
            "rotation": 0.0,
            "translation": {
                "X": -240.0,
                "Y": 45.0
            }
        },
        "Sprite": {
            "color": {
                "r": 255,
                "g": 255,
                "b": 255,
                "a": 255
            },
            "sprite": 2,
            "texture": "Textures\\Icons\\cursors\\UI_Cursor_Mouse_0001.png",
            "layer": 5
        }
    },
    {
        "General": {
            "name": "NEW Entity 1",
            "tag": 8,
            "subtag": 0,
            "isActive": true
        },
        "Transform": {
            "scale": {
                "X": 50.0,
                "Y": 50.0
            },
            "rotation": 0.0,
            "translation": {
                "X": -120.0,
                "Y": 75.0
            }
        },
        "Sprite": {
            "color": {
                "r": 255,
                "g": 255,
                "b": 255,
                "a": 255
            },
            "sprite": 2,
            "texture": "Textures\\Icons\\sendIcon.png",
            "layer": 6
        }
    },
    {
        "General": {
            "name": "NEW Entity 2",
            "tag": 8,
            "subtag": 0,
            "isActive": true
        },
        "Transform": {
            "scale": {
                "X": 50.0,
                "Y": 50.0
            },
            "rotation": 0.0,
            "translation": {
                "X": -120.0,
                "Y": 10.0
            }
        },
        "Sprite": {
            "color": {
                "r": 255,
                "g": 255,
                "b": 255,
                "a": 255
            },
            "sprite": 2,
            "texture": "Textures\\Icons\\dialogueIcon.png",
            "layer": 8
        }
    },
    {
        "General": {
            "name": "NEW Entity 4",
            "tag": 8,
            "subtag": 0,
            "isActive": true
        },
        "Transform": {
            "scale": {
                "X": 5.0,
                "Y": 20.0
            },
            "rotation": 0.0,
            "translation": {
                "X": -128.0,
                "Y": -132.0
            }
        },
        "Sprite": {
            "color": {
                "r": 255,
                "g": 255,
                "b": 255,
                "a": 255
            },
            "sprite": 2,
            "texture": "Textures\\Menu\\volume-button-3.png",
            "layer": 9
        }
    },
    {
        "General": {
            "name": "NEW Entity 5",
            "tag": 8,
            "subtag": 0,
            "isActive": true
        },
        "Transform": {
            "scale": {
                "X": 5.0,
                "Y": 20.0
            },
            "rotation": 0.0,
            "translation": {
                "X": -117.0,
                "Y": -132.0
            }
        },
        "Sprite": {
            "color": {
                "r": 255,
                "g": 255,
                "b": 255,
                "a": 255
            },
            "sprite": 2,
            "texture": "Textures\\Menu\\volume-button-3.png",
            "layer": 9
        }
    },
    {
        "General": {
            "name": "NEW Entity 6",
            "tag": 8,
            "subtag": 0,
            "isActive": true
        },
        "Transform": {
            "scale": {
                "X": 35.0,
                "Y": 35.0
            },
            "rotation": 0.7853981852531433,
            "translation": {
                "X": -122.0,
                "Y": -132.0
            }
        },
        "Sprite": {
            "color": {
                "r": 63,
                "g": 95,
                "b": 112,
                "a": 255
            },
            "sprite": 0,
            "texture": "",
            "layer": 8
        }
    }
]