{
        "General": {
            "name": "Btn",
            "tag": 5,
            "subtag": 1,
            "isActive": true
        },
        "Transform": {
            "scale": {
                "X": 400.0,
                "Y": 100.0
            },
            "rotation": 0.0,
            "translation": {
                "X": 0.0,
                "Y": 80.0
            }
        },
        "Sprite": {
            "color": {
                "r": 0,
                "g": 255,
                "b": 0,
                "a": 100
            },
            "sprite": 2,
            "texture": "Textures\\Menu\\button-1.png",
            "layer": 1
        },
        "RectCollider": {
            "centerOffset": {
                "X": 0.0,
                "Y": 0.0
            },
            "scaleOffset": {
                "X": 1.0,
                "Y": 1.0
            },
            "renderFlag": true
        },
        "Text": {
            "fontFile": "CaviarDreams",
            "text": "PLAY",
            "offset": {
                "X": -66.0,
                "Y": -25.0
            },
            "scale": 1.2,
            "color": {
                "r": 255,
                "g": 255,
                "b": 255,
                "a": 255
            }
        }


}